smartscraper/__init__.py
smartscraper/smart_scraper.py
smartscraper/utils.py
smartscraper-1.2.dist-info/METADATA
smartscraper-1.2.dist-info/WHEEL
smartscraper-1.2.dist-info/top_level.txt
smartscraper-1.2.dist-info/RECORD
