Metadata-Version: 2.1
Name: smartscraper
Version: 1.2
Summary: A Smart, Automatic, Fast and Lightweight Web Scraper for Python
Home-page: https://github.com/hidadeng/smartscraper
Author: DaDeng
Author-email: thunderhit@qq.com
License: MIT
Keywords: scraping,scraper,data crawler,crawler,spider
Platform: UNKNOWN
Requires-Python: >=3.5
Requires-Dist: requests
Requires-Dist: bs4
Requires-Dist: lxml
Requires-Dist: pandas
